flowlens_mcp_server/__init__.py
flowlens_mcp_server/dto/__init__.py
flowlens_mcp_server/dto/dto.py
flowlens_mcp_server/dto/dto_timeline.py
flowlens_mcp_server/flowlens_mcp/__init__.py
flowlens_mcp_server/flowlens_mcp/server_instance.py
flowlens_mcp_server/flowlens_mcp/tools.py
flowlens_mcp_server/models/__init__.py
flowlens_mcp_server/models/enums.py
flowlens_mcp_server/server.py
flowlens_mcp_server/service/__init__.py
flowlens_mcp_server/service/flow_lens.py
flowlens_mcp_server/service/timeline.py
flowlens_mcp_server/service/version.py
flowlens_mcp_server/utils/__init__.py
flowlens_mcp_server/utils/extension_compatibility/__init__.py
flowlens_mcp_server/utils/extension_compatibility/events_mapping.py
flowlens_mcp_server/utils/flow/__init__.py
flowlens_mcp_server/utils/flow/http_client.py
flowlens_mcp_server/utils/flow/local_zip.py
flowlens_mcp_server/utils/flow/registry.py
flowlens_mcp_server/utils/logger_setup.py
flowlens_mcp_server/utils/recording/__init__.py
flowlens_mcp_server/utils/recording/dom_snapshot_handler.py
flowlens_mcp_server/utils/recording/download.py
flowlens_mcp_server/utils/recording/video_handler.py
flowlens_mcp_server/utils/settings.py
flowlens_mcp_server/utils/timeline/__init__.py
flowlens_mcp_server/utils/timeline/events_processing.py
flowlens_mcp_server/utils/timeline/events_summarizer.py
flowlens_mcp_server/utils/timeline/loader.py
flowlens_mcp_server/utils/timeline/registry.py
flowlens_mcp_server-0.2.16.dist-info/METADATA
flowlens_mcp_server-0.2.16.dist-info/WHEEL
flowlens_mcp_server-0.2.16.dist-info/entry_points.txt
flowlens_mcp_server-0.2.16.dist-info/licenses/LICENSE.txt
flowlens_mcp_server-0.2.16.dist-info/RECORD
