Metadata-Version: 2.4
Name: flowlens-mcp-server
Version: 0.2.16
Summary: FlowLens MCP server for FlowLens created by Magentic AI
License: Apache 2.0
License-File: LICENSE.txt
Author: magentic
Author-email: flowlens@magentic.ai
Requires-Python: >=3.10,<4.0
Classifier: License :: Other/Proprietary License
Classifier: Programming Language :: Python :: 3
Classifier: Programming Language :: Python :: 3.10
Classifier: Programming Language :: Python :: 3.11
Classifier: Programming Language :: Python :: 3.12
Classifier: Programming Language :: Python :: 3.13
Classifier: Programming Language :: Python :: 3.14
Requires-Dist: aiofiles (>=24.1.0,<25.0.0)
Requires-Dist: aiohttp (>=3.12.15,<4.0.0)
Requires-Dist: build (>=1.3.0,<2.0.0)
Requires-Dist: fastmcp
Requires-Dist: opencv-python (>=4.12.0.88,<5.0.0.0)
Requires-Dist: pipx (>=1.8.0,<2.0.0)
Requires-Dist: starlette
Requires-Dist: twine (>=6.2.0,<7.0.0)
